{
  "Status": "OK",
  "FhirResource": {
  "type": "collection",
  "entry": [
    {
      "fullUrl": "urn:uuid:27e3b5b6-68e1-4ce0-a494-9e1c0fcf381f",
      "resource": {
        "id": "27e3b5b6-68e1-4ce0-a494-9e1c0fcf381f",
        "meta": {
          "profile": [
            "http://standardhealthrecord.org/fhir/StructureDefinition/shr-demographics-PersonOfRecord"
          ]
        },
        "text": {
          "status": "generated",
          "div": "<div>Generated by <a href=\"https://github.com/synthetichealth/synthea\">Synthea</a>. Version identifier: 4d02400401b9fab839e47bf5b2f1f6a8c683ab55</div>"
        },
        "extension": [
          {
            "url": "http://hl7.org/fhir/us/core/StructureDefinition/us-core-race",
            "valueCodeableConcept": {
              "coding": [
                {
                  "system": "http://hl7.org/fhir/v3/Race",
                  "code": "2054-5",
                  "display": "Black"
                }
              ],
              "text": "race"
            }
          },
          {
            "url": "http://hl7.org/fhir/us/core/StructureDefinition/us-core-ethnicity",
            "valueCodeableConcept": {
              "coding": [
                {
                  "system": "http://hl7.org/fhir/v3/Ethnicity",
                  "code": "2186-5",
                  "display": "Nonhispanic"
                }
              ],
              "text": "ethnicity"
            }
          },
          {
            "url": "http://hl7.org/fhir/StructureDefinition/birthPlace",
            "valueAddress": {
              "city": "Braintree Town",
              "state": "MA",
              "country": "US"
            }
          },
          {
            "url": "http://hl7.org/fhir/StructureDefinition/patient-mothersMaidenName",
            "valueString": "Fanny765 Nicolas801"
          },
          {
            "url": "http://hl7.org/fhir/us/core/StructureDefinition/us-core-birthsex",
            "valueCode": "F"
          },
          {
            "url": "http://hl7.org/fhir/StructureDefinition/patient-interpreterRequired",
            "valueBoolean": false
          },
          {
            "url": "http://standardhealthrecord.org/fhir/StructureDefinition/shr-actor-FictionalPerson-extension",
            "valueBoolean": true
          },
          {
            "url": "http://standardhealthrecord.org/fhir/StructureDefinition/shr-demographics-FathersName-extension",
            "valueHumanName": {
              "text": "Tess227 Douglas750"
            }
          },
          {
            "url": "http://standardhealthrecord.org/fhir/StructureDefinition/shr-demographics-SocialSecurityNumber-extension",
            "valueString": "999-34-2470"
          }
        ],
        "identifier": [
          {
            "system": "https://github.com/synthetichealth/synthea",
            "value": "d90b855c-8415-4244-88fa-1a262feee875"
          },
          {
            "type": {
              "coding": [
                {
                  "system": "http://hl7.org/fhir/identifier-type",
                  "code": "SB"
                }
              ]
            },
            "system": "http://hl7.org/fhir/sid/us-ssn",
            "value": "999342470"
          },
          {
            "type": {
              "coding": [
                {
                  "system": "http://hl7.org/fhir/v2/0203",
                  "code": "DL"
                }
              ]
            },
            "system": "urn:oid:2.16.840.1.113883.4.3.25",
            "value": "S99944444"
          }
        ],
        "name": [
          {
            "use": "official",
            "family": "Beahan56",
            "given": [
              "Audreanne496"
            ],
            "prefix": [
              "Mrs."
            ]
          },
          {
            "use": "maiden",
            "family": "Douglas750",
            "given": [
              "Audreanne496"
            ]
          }
        ],
        "telecom": [
          {
            "system": "phone",
            "value": "711.052.9486 x64448",
            "use": "home"
          }
        ],
        "gender": "female",
        "birthDate": "1981-12-03",
        "address": [
          {
            "extension": [
              {
                "extension": [
                  {
                    "url": "latitude",
                    "valueDecimal": 42.271984592429014
                  },
                  {
                    "url": "longitude",
                    "valueDecimal": -71.29772500569293
                  }
                ],
                "url": "http://hl7.org/fhir/StructureDefinition/geolocation"
              }
            ],
            "line": [
              "1081 Stehr Burgs"
            ],
            "city": "Wellesley",
            "state": "MA",
            "postalCode": "02457",
            "country": "US"
          }
        ],
        "maritalStatus": {
          "coding": [
            {
              "system": "http://hl7.org/fhir/v3/MaritalStatus",
              "code": "M"
            }
          ],
          "text": "M"
        },
        "multipleBirthBoolean": false,
        "communication": [
          {
            "language": {
              "coding": [
                {
                  "system": "http://hl7.org/fhir/ValueSet/languages",
                  "code": "en-US",
                  "display": "English (United States)"
                }
              ]
            }
          }
        ],
        "resourceType": "Patient"
      }
    },
    {
      "fullUrl": "urn:uuid:5e3c476e-1d30-45d4-a209-da699a1de776",
      "resource": {
        "id": "5e3c476e-1d30-45d4-a209-da699a1de776",
        "meta": {
          "profile": [
            "http://standardhealthrecord.org/fhir/StructureDefinition/shr-actor-Organization"
          ]
        },
        "type": [
          {
            "coding": [
              {
                "system": "http://hl7.org/fhir/ValueSet/organization-type",
                "code": "prov",
                "display": "Healthcare Provider"
              }
            ],
            "text": "Healthcare Provider"
          }
        ],
        "name": "Synthetic Provider",
        "resourceType": "Organization"
      }
    },
    {
      "fullUrl": "urn:uuid:af09821f-8ab4-46fe-b961-2e265140acf0",
      "resource": {
        "id": "af09821f-8ab4-46fe-b961-2e265140acf0",
        "meta": {
          "profile": [
            "http://standardhealthrecord.org/fhir/StructureDefinition/shr-encounter-Encounter"
          ]
        },
        "status": "finished",
        "class": {
          "code": "ambulatory"
        },
        "type": [
          {
            "coding": [
              {
                "system": "http://snomed.info/sct",
                "code": "185345009"
              }
            ],
            "text": "Encounter for symptom"
          }
        ],
        "subject": {
          "reference": "urn:uuid:27e3b5b6-68e1-4ce0-a494-9e1c0fcf381f"
        },
        "period": {
          "start": "2010-06-17T08:28:23-07:00",
          "end": "2010-06-17T08:28:23-07:00"
        },
        "reason": {
          "coding": [
            {
              "system": "http://snomed.info/sct",
              "code": "444814009",
              "display": "Viral sinusitis (disorder)"
            }
          ]
        },
        "serviceProvider": {
          "reference": "urn:uuid:5e3c476e-1d30-45d4-a209-da699a1de776"
        },
        "resourceType": "Encounter"
      }
    },
    {
      "fullUrl": "urn:uuid:12c53f5d-479a-4c5c-9206-a88d28e1c1bd",
      "resource": {
        "id": "12c53f5d-479a-4c5c-9206-a88d28e1c1bd",
        "meta": {
          "profile": [
            "http://standardhealthrecord.org/fhir/StructureDefinition/shr-problem-Problem"
          ]
        },
        "clinicalStatus": "active",
        "verificationStatus": "confirmed",
        "code": {
          "coding": [
            {
              "system": "http://snomed.info/sct",
              "code": "444814009",
              "display": "Viral sinusitis (disorder)"
            }
          ],
          "text": "Viral sinusitis (disorder)"
        },
        "subject": {
          "reference": "urn:uuid:27e3b5b6-68e1-4ce0-a494-9e1c0fcf381f"
        },
        "context": {
          "reference": "urn:uuid:af09821f-8ab4-46fe-b961-2e265140acf0"
        },
        "onsetDateTime": "2010-06-11T07:19:33-07:00",
        "abatementDateTime": "2010-06-26T03:15:33-07:00",
        "assertedDate": "2010-06-11",
        "resourceType": "Condition"
      }
    },
    {
      "fullUrl": "urn:uuid:a5f959af-49c0-4608-8aae-a3a8fd329463",
      "resource": {
        "id": "a5f959af-49c0-4608-8aae-a3a8fd329463",
        "meta": {
          "profile": [
            "http://standardhealthrecord.org/fhir/StructureDefinition/shr-encounter-Encounter"
          ]
        },
        "status": "finished",
        "class": {
          "code": "ambulatory"
        },
        "type": [
          {
            "coding": [
              {
                "system": "http://snomed.info/sct",
                "code": "185345009"
              }
            ],
            "text": "Encounter for symptom"
          }
        ],
        "subject": {
          "reference": "urn:uuid:27e3b5b6-68e1-4ce0-a494-9e1c0fcf381f"
        },
        "period": {
          "start": "2011-06-04T22:35:11-07:00",
          "end": "2011-06-04T22:35:11-07:00"
        },
        "reason": {
          "coding": [
            {
              "system": "http://snomed.info/sct",
              "code": "444814009",
              "display": "Viral sinusitis (disorder)"
            }
          ]
        },
        "serviceProvider": {
          "reference": "urn:uuid:5e3c476e-1d30-45d4-a209-da699a1de776"
        },
        "resourceType": "Encounter"
      }
    },
    {
      "fullUrl": "urn:uuid:d3ac5942-c044-4e20-bfcc-a65b5309c0f5",
      "resource": {
        "id": "d3ac5942-c044-4e20-bfcc-a65b5309c0f5",
        "meta": {
          "profile": [
            "http://standardhealthrecord.org/fhir/StructureDefinition/shr-problem-Problem"
          ]
        },
        "clinicalStatus": "active",
        "verificationStatus": "confirmed",
        "code": {
          "coding": [
            {
              "system": "http://snomed.info/sct",
              "code": "444814009",
              "display": "Viral sinusitis (disorder)"
            }
          ],
          "text": "Viral sinusitis (disorder)"
        },
        "subject": {
          "reference": "urn:uuid:27e3b5b6-68e1-4ce0-a494-9e1c0fcf381f"
        },
        "context": {
          "reference": "urn:uuid:a5f959af-49c0-4608-8aae-a3a8fd329463"
        },
        "onsetDateTime": "2011-05-26T03:15:33-07:00",
        "abatementDateTime": "2011-06-26T07:11:34-07:00",
        "assertedDate": "2011-05-26",
        "resourceType": "Condition"
      }
    },
    {
      "resource": {
        "meta": {
          "profile": [
            "http://standardhealthrecord.org/fhir/StructureDefinition/shr-medication-Medication"
          ]
        },
        "code": {
          "coding": [
            {
              "system": "http://www.nlm.nih.gov/research/umls/rxnorm",
              "code": "824184",
              "display": " Amoxicillin 250 MG / Clavulanate 125 MG [Augmentin]"
            },
            {
              "system": "http://www.nlm.nih.gov/research/umls/rxnorm",
              "code": "313782",
              "display": "Acetaminophen 325 MG Oral Tablet"
            }
          ],
          "text": "Acetaminophen 325 MG Oral Tablet"
        },
        "resourceType": "Medication"
      }
    },
    {
      "resource": {
        "meta": {
          "profile": [
            "http://standardhealthrecord.org/fhir/StructureDefinition/shr-medication-MedicationPrescription"
          ]
        },
        "extension": [
          {
            "url": "http://standardhealthrecord.org/fhir/StructureDefinition/shr-base-ActionCode-extension",
            "valueCodeableConcept": {
              "coding": [
                {
                  "system": "http://snomed.info/sct",
                  "code": "33633005",
                  "display": "Prescription of drug (procedure)"
                }
              ],
              "text": "Prescription of drug (procedure)"
            }
          }
        ],
        "status": "stopped",
        "subject": {
          "reference": "urn:uuid:27e3b5b6-68e1-4ce0-a494-9e1c0fcf381f"
        },
        "context": {
          "reference": "urn:uuid:6acfb9b3-45bb-43d8-beed-a3a270eb25de"
        },
        "authoredOn": "2017-02-10",
        "reasonReference": [
          {
            "reference": "urn:uuid:12c53f5d-479a-4c5c-9206-a88d28e1c1bd"
          }
        ],
        "resourceType": "MedicationRequest",
        "dosageInstruction": [
          {
            "sequence": 1,
            "asNeededBoolean": true
          }
        ]
      }
    },
    {
      "fullUrl": "urn:uuid:47881f15-51f7-4d44-9a06-6e71a9bb0ee5",
      "resource": {
        "id": "47881f15-51f7-4d44-9a06-6e71a9bb0ee5",
        "meta": {
          "profile": [
            "http://standardhealthrecord.org/fhir/StructureDefinition/shr-encounter-Encounter"
          ]
        },
        "status": "finished",
        "class": {
          "code": "outpatient"
        },
        "type": [
          {
            "coding": [
              {
                "system": "http://snomed.info/sct",
                "code": "185349003"
              }
            ],
            "text": "Outpatient Encounter"
          }
        ],
        "subject": {
          "reference": "urn:uuid:27e3b5b6-68e1-4ce0-a494-9e1c0fcf381f"
        },
        "period": {
          "start": "2011-08-17T19:22:41-07:00",
          "end": "2011-08-17T20:22:41-07:00"
        },
        "serviceProvider": {
          "reference": "urn:uuid:5e3c476e-1d30-45d4-a209-da699a1de776"
        },
        "resourceType": "Encounter"
      }
    },
    {
      "fullUrl": "urn:uuid:edf73bfd-c53f-4b89-bf50-2c4d6cfc79f9",
      "resource": {
        "id": "edf73bfd-c53f-4b89-bf50-2c4d6cfc79f9",
        "meta": {
          "profile": [
            "http://standardhealthrecord.org/fhir/StructureDefinition/shr-observation-Observation",
            "http://standardhealthrecord.org/fhir/StructureDefinition/shr-vital-VitalSign",
            "http://standardhealthrecord.org/fhir/StructureDefinition/shr-vital-BodyHeight"
          ]
        },
        "status": "final",
        "category": [
          {
            "coding": [
              {
                "system": "http://hl7.org/fhir/observation-category",
                "code": "vital-signs"
              }
            ]
          }
        ],
        "code": {
          "coding": [
            {
              "system": "http://loinc.org",
              "code": "8302-2",
              "display": "Body Height"
            }
          ],
          "text": "Body Height"
        },
        "subject": {
          "reference": "urn:uuid:27e3b5b6-68e1-4ce0-a494-9e1c0fcf381f"
        },
        "context": {
          "reference": "urn:uuid:47881f15-51f7-4d44-9a06-6e71a9bb0ee5"
        },
        "effectiveDateTime": "2011-08-17T19:22:41-07:00",
        "issued": "2011-08-17T19:22:41-07:00",
        "valueQuantity": {
          "value": 173.83589049809515,
          "unit": "cm",
          "system": "http://unitsofmeasure.org/",
          "code": "cm"
        },
        "resourceType": "Observation"
      }
    },
    {
      "fullUrl": "urn:uuid:87be38f1-c158-4cb1-b577-94059ce19ab4",
      "resource": {
        "id": "87be38f1-c158-4cb1-b577-94059ce19ab4",
        "meta": {
          "profile": [
            "http://standardhealthrecord.org/fhir/StructureDefinition/shr-observation-Observation",
            "http://standardhealthrecord.org/fhir/StructureDefinition/shr-vital-VitalSign",
            "http://standardhealthrecord.org/fhir/StructureDefinition/shr-vital-BodyWeight"
          ]
        },
        "status": "final",
        "category": [
          {
            "coding": [
              {
                "system": "http://hl7.org/fhir/observation-category",
                "code": "vital-signs"
              }
            ]
          }
        ],
        "code": {
          "coding": [
            {
              "system": "http://loinc.org",
              "code": "29463-7",
              "display": "Body Weight"
            }
          ],
          "text": "Body Weight"
        },
        "subject": {
          "reference": "urn:uuid:27e3b5b6-68e1-4ce0-a494-9e1c0fcf381f"
        },
        "context": {
          "reference": "urn:uuid:47881f15-51f7-4d44-9a06-6e71a9bb0ee5"
        },
        "effectiveDateTime": "2011-08-17T19:22:41-07:00",
        "issued": "2011-08-17T19:22:41-07:00",
        "valueQuantity": {
          "value": 71.21537452960281,
          "unit": "kg",
          "system": "http://unitsofmeasure.org/",
          "code": "kg"
        },
        "resourceType": "Observation"
      }
    },
    {
      "fullUrl": "urn:uuid:f064e5e2-7922-40ef-b043-36fc10fb2a65",
      "resource": {
        "id": "f064e5e2-7922-40ef-b043-36fc10fb2a65",
        "meta": {
          "profile": [
            "http://standardhealthrecord.org/fhir/StructureDefinition/shr-observation-Observation",
            "http://standardhealthrecord.org/fhir/StructureDefinition/shr-vital-VitalSign",
            "http://standardhealthrecord.org/fhir/StructureDefinition/shr-vital-BodyMassIndex"
          ]
        },
        "status": "final",
        "category": [
          {
            "coding": [
              {
                "system": "http://hl7.org/fhir/observation-category",
                "code": "vital-signs"
              }
            ]
          }
        ],
        "code": {
          "coding": [
            {
              "system": "http://loinc.org",
              "code": "39156-5",
              "display": "Body Mass Index"
            }
          ],
          "text": "Body Mass Index"
        },
        "subject": {
          "reference": "urn:uuid:27e3b5b6-68e1-4ce0-a494-9e1c0fcf381f"
        },
        "context": {
          "reference": "urn:uuid:47881f15-51f7-4d44-9a06-6e71a9bb0ee5"
        },
        "effectiveDateTime": "2011-08-17T19:22:41-07:00",
        "issued": "2011-08-17T19:22:41-07:00",
        "valueQuantity": {
          "value": 23.566488150912264,
          "unit": "kg/m2",
          "system": "http://unitsofmeasure.org/",
          "code": "kg/m2"
        },
        "resourceType": "Observation"
      }
    },
    {
      "fullUrl": "urn:uuid:8bdaaad9-986a-4519-8437-26c6bdc0b62c",
      "resource": {
        "id": "8bdaaad9-986a-4519-8437-26c6bdc0b62c",
        "meta": {
          "profile": [
            "http://standardhealthrecord.org/fhir/StructureDefinition/shr-observation-Observation",
            "http://standardhealthrecord.org/fhir/StructureDefinition/shr-vital-BloodPressure"
          ]
        },
        "status": "final",
        "category": [
          {
            "coding": [
              {
                "system": "http://hl7.org/fhir/observation-category",
                "code": "vital-signs"
              }
            ]
          }
        ],
        "code": {
          "coding": [
            {
              "system": "http://loinc.org",
              "code": "55284-4",
              "display": "Blood Pressure"
            }
          ]
        },
        "subject": {
          "reference": "urn:uuid:27e3b5b6-68e1-4ce0-a494-9e1c0fcf381f"
        },
        "context": {
          "reference": "urn:uuid:47881f15-51f7-4d44-9a06-6e71a9bb0ee5"
        },
        "effectiveDateTime": "2011-08-17T19:22:41-07:00",
        "issued": "2011-08-17T19:22:41-07:00",
        "component": [
          {
            "code": {
              "coding": [
                {
                  "system": "http://loinc.org",
                  "code": "8480-6",
                  "display": "Systolic Blood Pressure"
                }
              ],
              "text": "Systolic Blood Pressure"
            },
            "valueQuantity": {
              "value": 131,
              "unit": "mmHg",
              "system": "http://unitsofmeasure.org/",
              "code": "mmHg"
            }
          },
          {
            "code": {
              "coding": [
                {
                  "system": "http://loinc.org",
                  "code": "8462-4",
                  "display": "Diastolic Blood Pressure"
                }
              ],
              "text": "Diastolic Blood Pressure"
            },
            "valueQuantity": {
              "value": 74,
              "unit": "mmHg",
              "system": "http://unitsofmeasure.org/",
              "code": "mmHg"
            }
          }
        ],
        "resourceType": "Observation"
      }
    },
    {
      "resource": {
        "meta": {
          "profile": [
            "http://standardhealthrecord.org/fhir/StructureDefinition/shr-procedure-Procedure"
          ]
        },
        "extension": [
          {
            "url": "http://standardhealthrecord.org/fhir/StructureDefinition/shr-core-CodeableConcept-extension",
            "valueCodeableConcept": {
              "coding": [
                {
                  "system": "http://snomed.info/sct",
                  "code": "428191000124101",
                  "display": "Documentation of current medications"
                }
              ],
              "text": "Documentation of current medications"
            }
          },
          {
            "url": "http://standardhealthrecord.org/fhir/StructureDefinition/shr-core-CodeableConcept-extension",
            "valueCodeableConcept": {
              "coding": [
                {
                  "system": "http://snomed.info/sct",
                  "code": "252160004",
                  "display": "Standard pregnancy test"
                }
              ],
              "text": "Standard pregnancy test"
            }
          },
          {
            "url": "http://standardhealthrecord.org/fhir/StructureDefinition/shr-core-CodeableConcept-extension",
            "valueCodeableConcept": {
              "coding": [
                {
                  "system": "http://snomed.info/sct",
                  "code": "31208007",
                  "display": "Medical induction of labor"
                }
              ],
              "text": "Medical induction of labor"
            }
          },
          {
            "url": "http://standardhealthrecord.org/fhir/StructureDefinition/shr-core-CodeableConcept-extension",
            "valueCodeableConcept": {
              "coding": [
                {
                  "system": "http://snomed.info/sct",
                  "code": "11466000",
                  "display": "Cesarean section"
                }
              ],
              "text": "Cesarean section"
            }
          },
          {
            "url": "http://standardhealthrecord.org/fhir/StructureDefinition/shr-core-CodeableConcept-extension",
            "valueCodeableConcept": {
              "coding": [
                {
                  "system": "http://snomed.info/sct",
                  "code": "287664005",
                  "display": "Bilateral tubal ligation"
                }
              ],
              "text": "Bilateral tubal ligation"
            }
          }
        ],
        "status": "completed",
        "code": {
          "coding": [
            {
              "system": "http://snomed.info/sct",
              "code": "428191000124101",
              "display": "Documentation of current medications"
            },
            {
              "system": "http://snomed.info/sct",
              "code": "252160004",
              "display": "Standard pregnancy test"
            },
            {
              "system": "http://snomed.info/sct",
              "code": "31208007",
              "display": "Medical induction of labor"
            },
            {
              "system": "http://snomed.info/sct",
              "code": "11466000",
              "display": "Cesarean section"
            },
            {
              "system": "http://snomed.info/sct",
              "code": "287664005",
              "display": "Bilateral tubal ligation"
            }
          ],
          "text": "Bilateral tubal ligation"
        },
        "subject": {
          "reference": "urn:uuid:27e3b5b6-68e1-4ce0-a494-9e1c0fcf381f"
        },
        "context": {
          "reference": "urn:uuid:d38c387e-1286-42b6-ae04-2e49af0c4d8c"
        },
        "performedDateTime": "2013-05-16T12:53:39-07:00",
        "resourceType": "Procedure",
        "reasonReference": {
          "reference": "urn:uuid:51b6e6ac-c0cf-417b-8efb-a0f49bf46a97",
          "display": "Normal pregnancy"
        },
        "performedPeriod": {
          "start": "2013-06-06T03:38:28-07:00",
          "end": "2013-06-06T06:20:53-07:00"
        }
      }
    },
    {
      "resource": {
        "meta": {
          "profile": [
            "http://standardhealthrecord.org/fhir/StructureDefinition/shr-immunization-Immunization"
          ]
        },
        "status": "completed",
        "notGiven": false,
        "vaccineCode": {
          "coding": [
            {
              "system": "http://hl7.org/fhir/sid/cvx",
              "code": "140",
              "display": "Influenza, seasonal, injectable, preservative free"
            },
            {
              "system": "http://hl7.org/fhir/sid/cvx",
              "code": "113",
              "display": "Td (adult) preservative free"
            }
          ],
          "text": "Td (adult) preservative free"
        },
        "patient": {
          "reference": "urn:uuid:27e3b5b6-68e1-4ce0-a494-9e1c0fcf381f"
        },
        "encounter": {
          "reference": "urn:uuid:61e7ce8e-171b-4b54-9dfc-042d7add08fb"
        },
        "date": "2014-12-20T05:59:44-08:00",
        "primarySource": true,
        "resourceType": "Immunization"
      }
    },
    {
      "fullUrl": "urn:uuid:58ea9dfd-ff70-42e4-9a98-801414430095",
      "resource": {
        "id": "58ea9dfd-ff70-42e4-9a98-801414430095",
        "meta": {
          "profile": [
            "http://standardhealthrecord.org/fhir/StructureDefinition/shr-encounter-Encounter"
          ]
        },
        "status": "finished",
        "class": {
          "code": "ambulatory"
        },
        "type": [
          {
            "coding": [
              {
                "system": "http://snomed.info/sct",
                "code": "424441002"
              }
            ],
            "text": "Prenatal initial visit"
          }
        ],
        "subject": {
          "reference": "urn:uuid:27e3b5b6-68e1-4ce0-a494-9e1c0fcf381f"
        },
        "period": {
          "start": "2012-10-04T12:53:39-07:00",
          "end": "2012-10-04T12:53:39-07:00"
        },
        "reason": {
          "coding": [
            {
              "system": "http://snomed.info/sct",
              "code": "72892002",
              "display": "Normal pregnancy"
            }
          ]
        },
        "serviceProvider": {
          "reference": "urn:uuid:5e3c476e-1d30-45d4-a209-da699a1de776"
        },
        "resourceType": "Encounter"
      }
    },
    {
      "fullUrl": "urn:uuid:51b6e6ac-c0cf-417b-8efb-a0f49bf46a97",
      "resource": {
        "id": "51b6e6ac-c0cf-417b-8efb-a0f49bf46a97",
        "meta": {
          "profile": [
            "http://standardhealthrecord.org/fhir/StructureDefinition/shr-problem-Problem"
          ]
        },
        "clinicalStatus": "active",
        "verificationStatus": "confirmed",
        "code": {
          "coding": [
            {
              "system": "http://snomed.info/sct",
              "code": "72892002",
              "display": "Normal pregnancy"
            }
          ],
          "text": "Normal pregnancy"
        },
        "subject": {
          "reference": "urn:uuid:27e3b5b6-68e1-4ce0-a494-9e1c0fcf381f"
        },
        "context": {
          "reference": "urn:uuid:58ea9dfd-ff70-42e4-9a98-801414430095"
        },
        "onsetDateTime": "2012-10-04T12:53:39-07:00",
        "abatementDateTime": "2013-05-16T12:53:39-07:00",
        "assertedDate": "2012-10-04",
        "resourceType": "Condition"
      }
    },
    {
      "resource": {
        "status": "completed",
        "category": [
          {
            "coding": [
              {
                "system": "http://snomed.info/sct",
                "code": "134435003",
                "display": "Routine antenatal care"
              }
            ]
          },
          {
            "coding": [
              {
                "system": "http://snomed.info/sct",
                "code": "787301000000101",
                "display": "Surgery care management"
              }
            ]
          },
          {
            "coding": [
              {
                "system": "http://snomed.info/sct",
                "code": "91251008",
                "display": "Physical therapy procedure"
              }
            ]
          }
        ],
        "subject": {
          "reference": "urn:uuid:27e3b5b6-68e1-4ce0-a494-9e1c0fcf381f"
        },
        "context": {
          "reference": "urn:uuid:6acfb9b3-45bb-43d8-beed-a3a270eb25de"
        },
        "period": {
          "start": "2017-02-10",
          "end": "2017-03-22"
        },
        "addresses": [
          {
            "reference": "urn:uuid:51b6e6ac-c0cf-417b-8efb-a0f49bf46a97"
          },
          {
            "reference": "urn:uuid:f8d420af-9a65-4b63-b943-ec06de062040"
          }
        ],
        "activity": [
          {
            "detail": {
              "code": {
                "coding": [
                  {
                    "system": "http://snomed.info/sct",
                    "code": "135892000",
                    "display": "Antenatal education"
                  }
                ]
              },
              "status": "completed"
            }
          },
          {
            "detail": {
              "code": {
                "coding": [
                  {
                    "system": "http://snomed.info/sct",
                    "code": "226060000",
                    "display": "Stress management"
                  }
                ]
              },
              "status": "completed"
            }
          },
          {
            "detail": {
              "code": {
                "coding": [
                  {
                    "system": "http://snomed.info/sct",
                    "code": "171054004",
                    "display": "Pregnancy diet education"
                  }
                ]
              },
              "status": "completed"
            }
          },
          {
            "detail": {
              "code": {
                "coding": [
                  {
                    "system": "http://snomed.info/sct",
                    "code": "183051005",
                    "display": "Recommendation to rest"
                  }
                ]
              },
              "status": "completed"
            }
          },
          {
            "detail": {
              "code": {
                "coding": [
                  {
                    "system": "http://snomed.info/sct",
                    "code": "243077000",
                    "display": "Recommendation to limit sexual activity"
                  }
                ]
              },
              "status": "completed"
            }
          },
          {
            "detail": {
              "code": {
                "coding": [
                  {
                    "system": "http://snomed.info/sct",
                    "code": "229586001",
                    "display": "Rest, ice, compression and elevation treatment programme"
                  }
                ]
              },
              "status": "completed"
            }
          },
          {
            "detail": {
              "code": {
                "coding": [
                  {
                    "system": "http://snomed.info/sct",
                    "code": "229070002",
                    "display": "Stretching exercises"
                  }
                ]
              },
              "status": "completed"
            }
          }
        ],
        "resourceType": "CarePlan"
      }
    },
    {
      "fullUrl": "urn:uuid:2198cede-bcf2-4e68-a7c1-cc39355d4710",
      "resource": {
        "id": "2198cede-bcf2-4e68-a7c1-cc39355d4710",
        "meta": {
          "profile": [
            "http://standardhealthrecord.org/fhir/StructureDefinition/shr-encounter-Encounter"
          ]
        },
        "status": "finished",
        "class": {
          "code": "ambulatory"
        },
        "type": [
          {
            "coding": [
              {
                "system": "http://snomed.info/sct",
                "code": "424619006"
              }
            ],
            "text": "Prenatal visit"
          }
        ],
        "subject": {
          "reference": "urn:uuid:27e3b5b6-68e1-4ce0-a494-9e1c0fcf381f"
        },
        "period": {
          "start": "2012-11-08T12:53:39-08:00",
          "end": "2012-11-08T12:53:39-08:00"
        },
        "reason": {
          "coding": [
            {
              "system": "http://snomed.info/sct",
              "code": "72892002",
              "display": "Normal pregnancy"
            }
          ]
        },
        "serviceProvider": {
          "reference": "urn:uuid:5e3c476e-1d30-45d4-a209-da699a1de776"
        },
        "resourceType": "Encounter"
      }
    },
    {
      "fullUrl": "urn:uuid:f75f8f6c-7834-4b7c-93df-6991d4c306c6",
      "resource": {
        "id": "f75f8f6c-7834-4b7c-93df-6991d4c306c6",
        "meta": {
          "profile": [
            "http://standardhealthrecord.org/fhir/StructureDefinition/shr-encounter-Encounter"
          ]
        },
        "status": "finished",
        "class": {
          "code": "ambulatory"
        },
        "type": [
          {
            "coding": [
              {
                "system": "http://snomed.info/sct",
                "code": "424619006"
              }
            ],
            "text": "Prenatal visit"
          }
        ],
        "subject": {
          "reference": "urn:uuid:27e3b5b6-68e1-4ce0-a494-9e1c0fcf381f"
        },
        "period": {
          "start": "2013-01-24T12:53:39-08:00",
          "end": "2013-01-24T12:53:39-08:00"
        },
        "reason": {
          "coding": [
            {
              "system": "http://snomed.info/sct",
              "code": "72892002",
              "display": "Normal pregnancy"
            }
          ]
        },
        "serviceProvider": {
          "reference": "urn:uuid:5e3c476e-1d30-45d4-a209-da699a1de776"
        },
        "resourceType": "Encounter"
      }
    },
    {
      "fullUrl": "urn:uuid:79473e93-c250-48ea-8d74-844ffd0cb65f",
      "resource": {
        "id": "79473e93-c250-48ea-8d74-844ffd0cb65f",
        "meta": {
          "profile": [
            "http://standardhealthrecord.org/fhir/StructureDefinition/shr-encounter-Encounter"
          ]
        },
        "status": "finished",
        "class": {
          "code": "ambulatory"
        },
        "type": [
          {
            "coding": [
              {
                "system": "http://snomed.info/sct",
                "code": "424619006"
              }
            ],
            "text": "Prenatal visit"
          }
        ],
        "subject": {
          "reference": "urn:uuid:27e3b5b6-68e1-4ce0-a494-9e1c0fcf381f"
        },
        "period": {
          "start": "2013-03-07T12:53:39-08:00",
          "end": "2013-03-07T12:53:39-08:00"
        },
        "reason": {
          "coding": [
            {
              "system": "http://snomed.info/sct",
              "code": "72892002",
              "display": "Normal pregnancy"
            }
          ]
        },
        "serviceProvider": {
          "reference": "urn:uuid:5e3c476e-1d30-45d4-a209-da699a1de776"
        },
        "resourceType": "Encounter"
      }
    },
    {
      "fullUrl": "urn:uuid:e4c7cd01-4c5c-460c-b286-899e725b0f74",
      "resource": {
        "id": "e4c7cd01-4c5c-460c-b286-899e725b0f74",
        "meta": {
          "profile": [
            "http://standardhealthrecord.org/fhir/StructureDefinition/shr-encounter-Encounter"
          ]
        },
        "status": "finished",
        "class": {
          "code": "ambulatory"
        },
        "type": [
          {
            "coding": [
              {
                "system": "http://snomed.info/sct",
                "code": "424619006"
              }
            ],
            "text": "Prenatal visit"
          }
        ],
        "subject": {
          "reference": "urn:uuid:27e3b5b6-68e1-4ce0-a494-9e1c0fcf381f"
        },
        "period": {
          "start": "2013-04-04T12:53:39-07:00",
          "end": "2013-04-04T12:53:39-07:00"
        },
        "reason": {
          "coding": [
            {
              "system": "http://snomed.info/sct",
              "code": "72892002",
              "display": "Normal pregnancy"
            }
          ]
        },
        "serviceProvider": {
          "reference": "urn:uuid:5e3c476e-1d30-45d4-a209-da699a1de776"
        },
        "resourceType": "Encounter"
      }
    },
    {
      "fullUrl": "urn:uuid:c78810c1-5a48-4ddf-98f2-f22225214025",
      "resource": {
        "id": "c78810c1-5a48-4ddf-98f2-f22225214025",
        "meta": {
          "profile": [
            "http://standardhealthrecord.org/fhir/StructureDefinition/shr-encounter-Encounter"
          ]
        },
        "status": "finished",
        "class": {
          "code": "ambulatory"
        },
        "type": [
          {
            "coding": [
              {
                "system": "http://snomed.info/sct",
                "code": "424619006"
              }
            ],
            "text": "Prenatal visit"
          }
        ],
        "subject": {
          "reference": "urn:uuid:27e3b5b6-68e1-4ce0-a494-9e1c0fcf381f"
        },
        "period": {
          "start": "2013-04-18T12:53:39-07:00",
          "end": "2013-04-18T12:53:39-07:00"
        },
        "reason": {
          "coding": [
            {
              "system": "http://snomed.info/sct",
              "code": "72892002",
              "display": "Normal pregnancy"
            }
          ]
        },
        "serviceProvider": {
          "reference": "urn:uuid:5e3c476e-1d30-45d4-a209-da699a1de776"
        },
        "resourceType": "Encounter"
      }
    },
    {
      "fullUrl": "urn:uuid:ab6bf595-97ff-465c-a64b-3afc2520badb",
      "resource": {
        "id": "ab6bf595-97ff-465c-a64b-3afc2520badb",
        "meta": {
          "profile": [
            "http://standardhealthrecord.org/fhir/StructureDefinition/shr-encounter-Encounter"
          ]
        },
        "status": "finished",
        "class": {
          "code": "ambulatory"
        },
        "type": [
          {
            "coding": [
              {
                "system": "http://snomed.info/sct",
                "code": "424619006"
              }
            ],
            "text": "Prenatal visit"
          }
        ],
        "subject": {
          "reference": "urn:uuid:27e3b5b6-68e1-4ce0-a494-9e1c0fcf381f"
        },
        "period": {
          "start": "2013-04-25T12:53:39-07:00",
          "end": "2013-04-25T12:53:39-07:00"
        },
        "reason": {
          "coding": [
            {
              "system": "http://snomed.info/sct",
              "code": "72892002",
              "display": "Normal pregnancy"
            }
          ]
        },
        "serviceProvider": {
          "reference": "urn:uuid:5e3c476e-1d30-45d4-a209-da699a1de776"
        },
        "resourceType": "Encounter"
      }
    },
    {
      "fullUrl": "urn:uuid:673bebb0-def6-4d27-af16-59c85913498b",
      "resource": {
        "id": "673bebb0-def6-4d27-af16-59c85913498b",
        "meta": {
          "profile": [
            "http://standardhealthrecord.org/fhir/StructureDefinition/shr-encounter-Encounter"
          ]
        },
        "status": "finished",
        "class": {
          "code": "ambulatory"
        },
        "type": [
          {
            "coding": [
              {
                "system": "http://snomed.info/sct",
                "code": "424619006"
              }
            ],
            "text": "Prenatal visit"
          }
        ],
        "subject": {
          "reference": "urn:uuid:27e3b5b6-68e1-4ce0-a494-9e1c0fcf381f"
        },
        "period": {
          "start": "2013-05-02T12:53:39-07:00",
          "end": "2013-05-02T12:53:39-07:00"
        },
        "reason": {
          "coding": [
            {
              "system": "http://snomed.info/sct",
              "code": "72892002",
              "display": "Normal pregnancy"
            }
          ]
        },
        "serviceProvider": {
          "reference": "urn:uuid:5e3c476e-1d30-45d4-a209-da699a1de776"
        },
        "resourceType": "Encounter"
      }
    },
    {
      "fullUrl": "urn:uuid:192d0835-ed4b-4f21-a1ea-d554901255e2",
      "resource": {
        "id": "192d0835-ed4b-4f21-a1ea-d554901255e2",
        "meta": {
          "profile": [
            "http://standardhealthrecord.org/fhir/StructureDefinition/shr-encounter-Encounter"
          ]
        },
        "status": "finished",
        "class": {
          "code": "ambulatory"
        },
        "type": [
          {
            "coding": [
              {
                "system": "http://snomed.info/sct",
                "code": "424619006"
              }
            ],
            "text": "Prenatal visit"
          }
        ],
        "subject": {
          "reference": "urn:uuid:27e3b5b6-68e1-4ce0-a494-9e1c0fcf381f"
        },
        "period": {
          "start": "2013-05-09T12:53:39-07:00",
          "end": "2013-05-09T12:53:39-07:00"
        },
        "reason": {
          "coding": [
            {
              "system": "http://snomed.info/sct",
              "code": "72892002",
              "display": "Normal pregnancy"
            }
          ]
        },
        "serviceProvider": {
          "reference": "urn:uuid:5e3c476e-1d30-45d4-a209-da699a1de776"
        },
        "resourceType": "Encounter"
      }
    },
    {
      "fullUrl": "urn:uuid:ef4e639d-e580-4251-b5e5-864d28c2fd42",
      "resource": {
        "id": "ef4e639d-e580-4251-b5e5-864d28c2fd42",
        "meta": {
          "profile": [
            "http://standardhealthrecord.org/fhir/StructureDefinition/shr-encounter-Encounter"
          ]
        },
        "status": "finished",
        "class": {
          "code": "ambulatory"
        },
        "type": [
          {
            "coding": [
              {
                "system": "http://snomed.info/sct",
                "code": "424619006"
              }
            ],
            "text": "Prenatal visit"
          }
        ],
        "subject": {
          "reference": "urn:uuid:27e3b5b6-68e1-4ce0-a494-9e1c0fcf381f"
        },
        "period": {
          "start": "2013-05-16T12:53:39-07:00",
          "end": "2013-05-16T12:53:39-07:00"
        },
        "reason": {
          "coding": [
            {
              "system": "http://snomed.info/sct",
              "code": "72892002",
              "display": "Normal pregnancy"
            }
          ]
        },
        "serviceProvider": {
          "reference": "urn:uuid:5e3c476e-1d30-45d4-a209-da699a1de776"
        },
        "resourceType": "Encounter"
      }
    },
    {
      "fullUrl": "urn:uuid:218d5a88-6728-4f7b-8319-758c9bc1bdbb",
      "resource": {
        "id": "218d5a88-6728-4f7b-8319-758c9bc1bdbb",
        "meta": {
          "profile": [
            "http://standardhealthrecord.org/fhir/StructureDefinition/shr-encounter-Encounter"
          ]
        },
        "status": "finished",
        "class": {
          "code": "emergency"
        },
        "type": [
          {
            "coding": [
              {
                "system": "http://snomed.info/sct",
                "code": "183460006"
              }
            ],
            "text": "Obstetric emergency hospital admission"
          }
        ],
        "subject": {
          "reference": "urn:uuid:27e3b5b6-68e1-4ce0-a494-9e1c0fcf381f"
        },
        "period": {
          "start": "2013-05-16T12:53:39-07:00",
          "end": "2013-05-16T12:53:39-07:00"
        },
        "reason": {
          "coding": [
            {
              "system": "http://snomed.info/sct",
              "code": "72892002",
              "display": "Normal pregnancy"
            }
          ]
        },
        "serviceProvider": {
          "reference": "urn:uuid:5e3c476e-1d30-45d4-a209-da699a1de776"
        },
        "resourceType": "Encounter"
      }
    },
    {
      "fullUrl": "urn:uuid:5262b4b6-6d17-4c31-99e3-c738eee2a1fb",
      "resource": {
        "id": "5262b4b6-6d17-4c31-99e3-c738eee2a1fb",
        "meta": {
          "profile": [
            "http://standardhealthrecord.org/fhir/StructureDefinition/shr-encounter-Encounter"
          ]
        },
        "status": "finished",
        "class": {
          "code": "outpatient"
        },
        "type": [
          {
            "coding": [
              {
                "system": "http://snomed.info/sct",
                "code": "698314001"
              }
            ],
            "text": "Consultation for treatment"
          }
        ],
        "subject": {
          "reference": "urn:uuid:27e3b5b6-68e1-4ce0-a494-9e1c0fcf381f"
        },
        "period": {
          "start": "2013-05-23T12:53:39-07:00",
          "end": "2013-05-23T12:53:39-07:00"
        },
        "serviceProvider": {
          "reference": "urn:uuid:5e3c476e-1d30-45d4-a209-da699a1de776"
        },
        "resourceType": "Encounter"
      }
    },
    {
      "fullUrl": "urn:uuid:d38c387e-1286-42b6-ae04-2e49af0c4d8c",
      "resource": {
        "id": "d38c387e-1286-42b6-ae04-2e49af0c4d8c",
        "meta": {
          "profile": [
            "http://standardhealthrecord.org/fhir/StructureDefinition/shr-encounter-Encounter"
          ]
        },
        "status": "finished",
        "class": {
          "code": "inpatient"
        },
        "type": [
          {
            "coding": [
              {
                "system": "http://snomed.info/sct",
                "code": "305408004"
              }
            ],
            "text": "Admission to surgical department"
          }
        ],
        "subject": {
          "reference": "urn:uuid:27e3b5b6-68e1-4ce0-a494-9e1c0fcf381f"
        },
        "period": {
          "start": "2013-06-06T03:38:28-07:00",
          "end": "2013-06-06T05:58:29-07:00"
        },
        "serviceProvider": {
          "reference": "urn:uuid:5e3c476e-1d30-45d4-a209-da699a1de776"
        },
        "resourceType": "Encounter"
      }
    },
    {
      "fullUrl": "urn:uuid:61e7ce8e-171b-4b54-9dfc-042d7add08fb",
      "resource": {
        "id": "61e7ce8e-171b-4b54-9dfc-042d7add08fb",
        "meta": {
          "profile": [
            "http://standardhealthrecord.org/fhir/StructureDefinition/shr-encounter-Encounter"
          ]
        },
        "status": "finished",
        "class": {
          "code": "outpatient"
        },
        "type": [
          {
            "coding": [
              {
                "system": "http://snomed.info/sct",
                "code": "185349003"
              }
            ],
            "text": "Outpatient Encounter"
          }
        ],
        "subject": {
          "reference": "urn:uuid:27e3b5b6-68e1-4ce0-a494-9e1c0fcf381f"
        },
        "period": {
          "start": "2014-12-20T05:59:44-08:00",
          "end": "2014-12-20T06:59:44-08:00"
        },
        "serviceProvider": {
          "reference": "urn:uuid:5e3c476e-1d30-45d4-a209-da699a1de776"
        },
        "resourceType": "Encounter"
      }
    },
    {
      "fullUrl": "urn:uuid:dc4bdd8e-61a9-444b-8e11-618a85de49a4",
      "resource": {
        "id": "dc4bdd8e-61a9-444b-8e11-618a85de49a4",
        "meta": {
          "profile": [
            "http://standardhealthrecord.org/fhir/StructureDefinition/shr-observation-Observation",
            "http://standardhealthrecord.org/fhir/StructureDefinition/shr-vital-VitalSign",
            "http://standardhealthrecord.org/fhir/StructureDefinition/shr-vital-BodyHeight"
          ]
        },
        "status": "final",
        "category": [
          {
            "coding": [
              {
                "system": "http://hl7.org/fhir/observation-category",
                "code": "vital-signs"
              }
            ]
          }
        ],
        "code": {
          "coding": [
            {
              "system": "http://loinc.org",
              "code": "8302-2",
              "display": "Body Height"
            }
          ],
          "text": "Body Height"
        },
        "subject": {
          "reference": "urn:uuid:27e3b5b6-68e1-4ce0-a494-9e1c0fcf381f"
        },
        "context": {
          "reference": "urn:uuid:61e7ce8e-171b-4b54-9dfc-042d7add08fb"
        },
        "effectiveDateTime": "2014-12-20T05:59:44-08:00",
        "issued": "2014-12-20T05:59:44-08:00",
        "valueQuantity": {
          "value": 173.83589049809515,
          "unit": "cm",
          "system": "http://unitsofmeasure.org/",
          "code": "cm"
        },
        "resourceType": "Observation"
      }
    },
    {
      "fullUrl": "urn:uuid:4b2e51d3-41a9-4f0f-9d95-ae52215f32fb",
      "resource": {
        "id": "4b2e51d3-41a9-4f0f-9d95-ae52215f32fb",
        "meta": {
          "profile": [
            "http://standardhealthrecord.org/fhir/StructureDefinition/shr-observation-Observation",
            "http://standardhealthrecord.org/fhir/StructureDefinition/shr-vital-VitalSign",
            "http://standardhealthrecord.org/fhir/StructureDefinition/shr-vital-BodyWeight"
          ]
        },
        "status": "final",
        "category": [
          {
            "coding": [
              {
                "system": "http://hl7.org/fhir/observation-category",
                "code": "vital-signs"
              }
            ]
          }
        ],
        "code": {
          "coding": [
            {
              "system": "http://loinc.org",
              "code": "29463-7",
              "display": "Body Weight"
            }
          ],
          "text": "Body Weight"
        },
        "subject": {
          "reference": "urn:uuid:27e3b5b6-68e1-4ce0-a494-9e1c0fcf381f"
        },
        "context": {
          "reference": "urn:uuid:61e7ce8e-171b-4b54-9dfc-042d7add08fb"
        },
        "effectiveDateTime": "2014-12-20T05:59:44-08:00",
        "issued": "2014-12-20T05:59:44-08:00",
        "valueQuantity": {
          "value": 75.97079116690796,
          "unit": "kg",
          "system": "http://unitsofmeasure.org/",
          "code": "kg"
        },
        "resourceType": "Observation"
      }
    },
    {
      "fullUrl": "urn:uuid:08be83b3-2cf9-4832-ad39-5a36b940fa8c",
      "resource": {
        "id": "08be83b3-2cf9-4832-ad39-5a36b940fa8c",
        "meta": {
          "profile": [
            "http://standardhealthrecord.org/fhir/StructureDefinition/shr-observation-Observation",
            "http://standardhealthrecord.org/fhir/StructureDefinition/shr-vital-VitalSign",
            "http://standardhealthrecord.org/fhir/StructureDefinition/shr-vital-BodyMassIndex"
          ]
        },
        "status": "final",
        "category": [
          {
            "coding": [
              {
                "system": "http://hl7.org/fhir/observation-category",
                "code": "vital-signs"
              }
            ]
          }
        ],
        "code": {
          "coding": [
            {
              "system": "http://loinc.org",
              "code": "39156-5",
              "display": "Body Mass Index"
            }
          ],
          "text": "Body Mass Index"
        },
        "subject": {
          "reference": "urn:uuid:27e3b5b6-68e1-4ce0-a494-9e1c0fcf381f"
        },
        "context": {
          "reference": "urn:uuid:61e7ce8e-171b-4b54-9dfc-042d7add08fb"
        },
        "effectiveDateTime": "2014-12-20T05:59:44-08:00",
        "issued": "2014-12-20T05:59:44-08:00",
        "valueQuantity": {
          "value": 25.140143707397726,
          "unit": "kg/m2",
          "system": "http://unitsofmeasure.org/",
          "code": "kg/m2"
        },
        "resourceType": "Observation"
      }
    },
    {
      "fullUrl": "urn:uuid:269c260e-7862-4dea-874d-9b08bcd4bbc3",
      "resource": {
        "id": "269c260e-7862-4dea-874d-9b08bcd4bbc3",
        "meta": {
          "profile": [
            "http://standardhealthrecord.org/fhir/StructureDefinition/shr-observation-Observation",
            "http://standardhealthrecord.org/fhir/StructureDefinition/shr-vital-BloodPressure"
          ]
        },
        "status": "final",
        "category": [
          {
            "coding": [
              {
                "system": "http://hl7.org/fhir/observation-category",
                "code": "vital-signs"
              }
            ]
          }
        ],
        "code": {
          "coding": [
            {
              "system": "http://loinc.org",
              "code": "55284-4",
              "display": "Blood Pressure"
            }
          ]
        },
        "subject": {
          "reference": "urn:uuid:27e3b5b6-68e1-4ce0-a494-9e1c0fcf381f"
        },
        "context": {
          "reference": "urn:uuid:61e7ce8e-171b-4b54-9dfc-042d7add08fb"
        },
        "effectiveDateTime": "2014-12-20T05:59:44-08:00",
        "issued": "2014-12-20T05:59:44-08:00",
        "component": [
          {
            "code": {
              "coding": [
                {
                  "system": "http://loinc.org",
                  "code": "8480-6",
                  "display": "Systolic Blood Pressure"
                }
              ],
              "text": "Systolic Blood Pressure"
            },
            "valueQuantity": {
              "value": 116,
              "unit": "mmHg",
              "system": "http://unitsofmeasure.org/",
              "code": "mmHg"
            }
          },
          {
            "code": {
              "coding": [
                {
                  "system": "http://loinc.org",
                  "code": "8462-4",
                  "display": "Diastolic Blood Pressure"
                }
              ],
              "text": "Diastolic Blood Pressure"
            },
            "valueQuantity": {
              "value": 81,
              "unit": "mmHg",
              "system": "http://unitsofmeasure.org/",
              "code": "mmHg"
            }
          }
        ],
        "resourceType": "Observation"
      }
    },
    {
      "fullUrl": "urn:uuid:b8c6013f-7a36-4705-ad98-4e434e967d9b",
      "resource": {
        "id": "b8c6013f-7a36-4705-ad98-4e434e967d9b",
        "meta": {
          "profile": [
            "http://standardhealthrecord.org/fhir/StructureDefinition/shr-observation-Observation"
          ]
        },
        "status": "final",
        "category": [
          {
            "coding": [
              {
                "system": "http://hl7.org/fhir/observation-category",
                "code": "laboratory"
              }
            ]
          }
        ],
        "code": {
          "coding": [
            {
              "system": "http://loinc.org",
              "code": "2093-3",
              "display": "Total Cholesterol"
            }
          ],
          "text": "Total Cholesterol"
        },
        "subject": {
          "reference": "urn:uuid:27e3b5b6-68e1-4ce0-a494-9e1c0fcf381f"
        },
        "context": {
          "reference": "urn:uuid:61e7ce8e-171b-4b54-9dfc-042d7add08fb"
        },
        "effectiveDateTime": "2014-12-20T05:59:44-08:00",
        "issued": "2014-12-20T05:59:44-08:00",
        "valueQuantity": {
          "value": 188,
          "unit": "mg/dL",
          "system": "http://unitsofmeasure.org/",
          "code": "mg/dL"
        },
        "resourceType": "Observation"
      }
    },
    {
      "fullUrl": "urn:uuid:85d1a4a0-2193-4576-a2bd-de27d3672736",
      "resource": {
        "id": "85d1a4a0-2193-4576-a2bd-de27d3672736",
        "meta": {
          "profile": [
            "http://standardhealthrecord.org/fhir/StructureDefinition/shr-observation-Observation"
          ]
        },
        "status": "final",
        "category": [
          {
            "coding": [
              {
                "system": "http://hl7.org/fhir/observation-category",
                "code": "laboratory"
              }
            ]
          }
        ],
        "code": {
          "coding": [
            {
              "system": "http://loinc.org",
              "code": "2571-8",
              "display": "Triglycerides"
            }
          ],
          "text": "Triglycerides"
        },
        "subject": {
          "reference": "urn:uuid:27e3b5b6-68e1-4ce0-a494-9e1c0fcf381f"
        },
        "context": {
          "reference": "urn:uuid:61e7ce8e-171b-4b54-9dfc-042d7add08fb"
        },
        "effectiveDateTime": "2014-12-20T05:59:44-08:00",
        "issued": "2014-12-20T05:59:44-08:00",
        "valueQuantity": {
          "value": 104,
          "unit": "mg/dL",
          "system": "http://unitsofmeasure.org/",
          "code": "mg/dL"
        },
        "resourceType": "Observation"
      }
    },
    {
      "fullUrl": "urn:uuid:bc1ada8e-d32b-46d0-bc9c-99d81640d94f",
      "resource": {
        "id": "bc1ada8e-d32b-46d0-bc9c-99d81640d94f",
        "meta": {
          "profile": [
            "http://standardhealthrecord.org/fhir/StructureDefinition/shr-observation-Observation"
          ]
        },
        "status": "final",
        "category": [
          {
            "coding": [
              {
                "system": "http://hl7.org/fhir/observation-category",
                "code": "laboratory"
              }
            ]
          }
        ],
        "code": {
          "coding": [
            {
              "system": "http://loinc.org",
              "code": "18262-6",
              "display": "Low Density Lipoprotein Cholesterol"
            }
          ],
          "text": "Low Density Lipoprotein Cholesterol"
        },
        "subject": {
          "reference": "urn:uuid:27e3b5b6-68e1-4ce0-a494-9e1c0fcf381f"
        },
        "context": {
          "reference": "urn:uuid:61e7ce8e-171b-4b54-9dfc-042d7add08fb"
        },
        "effectiveDateTime": "2014-12-20T05:59:44-08:00",
        "issued": "2014-12-20T05:59:44-08:00",
        "valueQuantity": {
          "value": 89,
          "unit": "mg/dL",
          "system": "http://unitsofmeasure.org/",
          "code": "mg/dL"
        },
        "resourceType": "Observation"
      }
    },
    {
      "fullUrl": "urn:uuid:84249cd0-4e76-4b51-b986-c891215ca4a6",
      "resource": {
        "id": "84249cd0-4e76-4b51-b986-c891215ca4a6",
        "meta": {
          "profile": [
            "http://standardhealthrecord.org/fhir/StructureDefinition/shr-observation-Observation"
          ]
        },
        "status": "final",
        "category": [
          {
            "coding": [
              {
                "system": "http://hl7.org/fhir/observation-category",
                "code": "laboratory"
              }
            ]
          }
        ],
        "code": {
          "coding": [
            {
              "system": "http://loinc.org",
              "code": "2085-9",
              "display": "High Density Lipoprotein Cholesterol"
            }
          ],
          "text": "High Density Lipoprotein Cholesterol"
        },
        "subject": {
          "reference": "urn:uuid:27e3b5b6-68e1-4ce0-a494-9e1c0fcf381f"
        },
        "context": {
          "reference": "urn:uuid:61e7ce8e-171b-4b54-9dfc-042d7add08fb"
        },
        "effectiveDateTime": "2014-12-20T05:59:44-08:00",
        "issued": "2014-12-20T05:59:44-08:00",
        "valueQuantity": {
          "value": 78,
          "unit": "mg/dL",
          "system": "http://unitsofmeasure.org/",
          "code": "mg/dL"
        },
        "resourceType": "Observation"
      }
    },
    {
      "fullUrl": "urn:uuid:f42aabc6-3e43-427d-85a3-6c4c72ad3126",
      "resource": {
        "id": "f42aabc6-3e43-427d-85a3-6c4c72ad3126",
        "meta": {
          "profile": [
            "http://standardhealthrecord.org/fhir/StructureDefinition/shr-observation-Panel"
          ]
        },
        "status": "final",
        "code": {
          "coding": [
            {
              "system": "http://loinc.org",
              "code": "57698-3",
              "display": "Lipid Panel"
            }
          ]
        },
        "subject": {
          "reference": "urn:uuid:27e3b5b6-68e1-4ce0-a494-9e1c0fcf381f"
        },
        "context": {
          "reference": "urn:uuid:61e7ce8e-171b-4b54-9dfc-042d7add08fb"
        },
        "effectiveDateTime": "2014-12-20T05:59:44-08:00",
        "issued": "2014-12-20T05:59:44-08:00",
        "result": [
          {
            "reference": "urn:uuid:b8c6013f-7a36-4705-ad98-4e434e967d9b",
            "display": "Total Cholesterol"
          },
          {
            "reference": "urn:uuid:85d1a4a0-2193-4576-a2bd-de27d3672736",
            "display": "Triglycerides"
          },
          {
            "reference": "urn:uuid:bc1ada8e-d32b-46d0-bc9c-99d81640d94f",
            "display": "Low Density Lipoprotein Cholesterol"
          },
          {
            "reference": "urn:uuid:84249cd0-4e76-4b51-b986-c891215ca4a6",
            "display": "High Density Lipoprotein Cholesterol"
          }
        ],
        "resourceType": "DiagnosticReport"
      }
    },
    {
      "fullUrl": "urn:uuid:b3e55f43-a98d-4e97-9698-259fd3ad53fe",
      "resource": {
        "id": "b3e55f43-a98d-4e97-9698-259fd3ad53fe",
        "meta": {
          "profile": [
            "http://standardhealthrecord.org/fhir/StructureDefinition/shr-encounter-Encounter"
          ]
        },
        "status": "finished",
        "class": {
          "code": "ambulatory"
        },
        "type": [
          {
            "coding": [
              {
                "system": "http://snomed.info/sct",
                "code": "185345009"
              }
            ],
            "text": "Encounter for symptom"
          }
        ],
        "subject": {
          "reference": "urn:uuid:27e3b5b6-68e1-4ce0-a494-9e1c0fcf381f"
        },
        "period": {
          "start": "2016-11-01T01:40:32-07:00",
          "end": "2016-11-01T01:40:32-07:00"
        },
        "reason": {
          "coding": [
            {
              "system": "http://snomed.info/sct",
              "code": "444814009",
              "display": "Viral sinusitis (disorder)"
            }
          ]
        },
        "serviceProvider": {
          "reference": "urn:uuid:5e3c476e-1d30-45d4-a209-da699a1de776"
        },
        "resourceType": "Encounter"
      }
    },
    {
      "fullUrl": "urn:uuid:d496956f-ff0b-4efa-b6c8-799d1780b56e",
      "resource": {
        "id": "d496956f-ff0b-4efa-b6c8-799d1780b56e",
        "meta": {
          "profile": [
            "http://standardhealthrecord.org/fhir/StructureDefinition/shr-problem-Problem"
          ]
        },
        "clinicalStatus": "active",
        "verificationStatus": "confirmed",
        "code": {
          "coding": [
            {
              "system": "http://snomed.info/sct",
              "code": "444814009",
              "display": "Viral sinusitis (disorder)"
            }
          ],
          "text": "Viral sinusitis (disorder)"
        },
        "subject": {
          "reference": "urn:uuid:27e3b5b6-68e1-4ce0-a494-9e1c0fcf381f"
        },
        "context": {
          "reference": "urn:uuid:b3e55f43-a98d-4e97-9698-259fd3ad53fe"
        },
        "onsetDateTime": "2016-10-26T07:11:34-07:00",
        "abatementDateTime": "2016-11-22T06:46:10-08:00",
        "assertedDate": "2016-10-26",
        "resourceType": "Condition"
      }
    },
    {
      "fullUrl": "urn:uuid:6acfb9b3-45bb-43d8-beed-a3a270eb25de",
      "resource": {
        "id": "6acfb9b3-45bb-43d8-beed-a3a270eb25de",
        "meta": {
          "profile": [
            "http://standardhealthrecord.org/fhir/StructureDefinition/shr-encounter-Encounter"
          ]
        },
        "status": "finished",
        "class": {
          "code": "emergency"
        },
        "type": [
          {
            "coding": [
              {
                "system": "http://snomed.info/sct",
                "code": "50849002"
              }
            ],
            "text": "Emergency room admission"
          }
        ],
        "subject": {
          "reference": "urn:uuid:27e3b5b6-68e1-4ce0-a494-9e1c0fcf381f"
        },
        "period": {
          "start": "2017-02-10T15:45:37-08:00",
          "end": "2017-02-10T15:45:37-08:00"
        },
        "serviceProvider": {
          "reference": "urn:uuid:5e3c476e-1d30-45d4-a209-da699a1de776"
        },
        "resourceType": "Encounter"
      }
    },
    {
      "fullUrl": "urn:uuid:f8d420af-9a65-4b63-b943-ec06de062040",
      "resource": {
        "id": "f8d420af-9a65-4b63-b943-ec06de062040",
        "meta": {
          "profile": [
            "http://standardhealthrecord.org/fhir/StructureDefinition/shr-problem-Problem"
          ]
        },
        "clinicalStatus": "active",
        "verificationStatus": "confirmed",
        "code": {
          "coding": [
            {
              "system": "http://snomed.info/sct",
              "code": "44465007",
              "display": "Sprain of ankle"
            }
          ],
          "text": "Sprain of ankle"
        },
        "subject": {
          "reference": "urn:uuid:27e3b5b6-68e1-4ce0-a494-9e1c0fcf381f"
        },
        "context": {
          "reference": "urn:uuid:6acfb9b3-45bb-43d8-beed-a3a270eb25de"
        },
        "onsetDateTime": "2017-02-10T15:45:37-08:00",
        "abatementDateTime": "2017-03-22T18:32:39-07:00",
        "assertedDate": "2017-02-10",
        "resourceType": "Condition"
      }
    }
  ],
  "resourceType": "Bundle"
}
}